mailbox_cleaner.py
mailbox_cleaner-0.1.0.dist-info/LICENSE
mailbox_cleaner-0.1.0.dist-info/METADATA
mailbox_cleaner-0.1.0.dist-info/WHEEL
mailbox_cleaner-0.1.0.dist-info/entry_points.txt
mailbox_cleaner-0.1.0.dist-info/top_level.txt
mailbox_cleaner-0.1.0.dist-info/RECORD
