Metadata-Version: 2.1
Name: mailbox-cleaner
Version: 0.1.0
Summary: Command line utility to clean IMAP folders
Home-page: https://github.com/adbenitez/mailbox_cleaner
Author: adbenitez
Author-email: adbenitez@hispanilandia.net
License: UNKNOWN
Keywords: cli email imap cleaner
Platform: UNKNOWN
Classifier: Development Status :: 4 - Beta
Classifier: Intended Audience :: End Users/Desktop
Classifier: License :: OSI Approved :: GNU General Public License v3 (GPLv3)
Classifier: Operating System :: POSIX
Classifier: Programming Language :: Python :: 3
Requires-Python: >=3.7
License-File: LICENSE
Requires-Dist: imap-tools (>=0.55.0)
Provides-Extra: dev
Requires-Dist: imap-tools (>=0.55.0) ; extra == 'dev'
Requires-Dist: pytest (>=7.1.2) ; extra == 'dev'
Requires-Dist: black (>=22.3.0) ; extra == 'dev'
Requires-Dist: mypy (>=0.960) ; extra == 'dev'
Requires-Dist: isort (>=5.10.1) ; extra == 'dev'
Requires-Dist: pylama (>=8.3.8) ; extra == 'dev'
Requires-Dist: types-pkg-resources (>=0.1.3) ; extra == 'dev'
Requires-Dist: types-setuptools (>=57.4.17) ; extra == 'dev'
Requires-Dist: pylint (==2.14.4) ; extra == 'dev'
Provides-Extra: test
Requires-Dist: pytest (>=7.1.2) ; extra == 'test'
